Workbook

Sheet Cover
B2: 3-Statement Integrated Model
B3: Subject: Microsoft Corporation (NASDAQ: MSFT) | Fiscal Year End: June 30
B4: Prepared by: Akul Veauli
B5: Date: August 23, 2026
B7: Fully-linked three-statement model covering FY2023A-FY2025A historicals and FY2026E-FY2030E projections. Revenue, margin, and balance-sheet drivers sit on the Assumptions tab; the Income Statement, Balance Sheet, and Cash Flow Statement are 100% formula-driven off those drivers and off each other. A dedicated Debt Schedule computes interest on beginning-of-period balances and sizes the revolver as an end-of-period plug, so the model contains no circular references and requires no iterative calculation. The Balance Sheet carries a live balance-check row (Total Assets less Total Liabilities & Equity) that equals 0.000 in every column, and the Checks tab consolidates all cross-statement ties.
B14: Color-code legend
B15: 123.4 | C15: Blue on yellow = hardcoded input
B16: =B15 | C16: Black = formula (same sheet)
B17: =IS!D19 | C17: Green = link from another tab
B19: Table of contents
B20: Assumptions | C20: All model drivers (blue inputs)
B21: IS | C21: Income statement, FY23A-FY30E
B22: BS | C22: Balance sheet + balance check
B23: CF | C23: Indirect cash flow statement
B24: DebtSchedule | C24: Long-term debt + revolver plug
B25: Checks | C25: Consolidated tie-out panel
B27: Key outputs (FY2030E)
B28: Revenue | C28: =IS!K7
B29: Net income | C29: =IS!K19
B30: Diluted EPS | C30: =IS!K24
B31: Total assets | C31: =BS!K17
B32: Ending cash & ST investments | C32: =CF!K42
B33: Consolidated check status | C33: =Checks!D15
B36: Sources
B37: MSFT FY2023-FY2025 Form 10-K filings (SEC accession nos. 000095017023035122, 000095017024087843, 000095017025100235); FY2025 10-K debt footnote / 10-Q (9/30/25) maturity schedule (weighted-avg coupon 4.52%); company earnings releases and IR disclosures. FY2025 unearned revenue and select opex/BS 'other' line detail are estimates reconciled to reported totals; see Assumptions tab and build notes for the reconciliation.

Sheet Assumptions
B2: Assumptions & Drivers
B3: ($ in millions except per-share, days, and % rows; blue = hardcoded input)
D5: FY2023A | E5: FY2024A | F5: FY2025A | G5: FY2026E | H5: FY2027E | I5: FY2028E | J5: FY2029E | K5: FY2030E
B7: Income Statement Drivers
B8: Revenue growth % | D8: n/a | E8: =IS!E7/IS!D7-1 | F8: =IS!F7/IS!E7-1 | G8: 0.16 | H8: 0.14 | I8: 0.12 | J8: 0.11 | K8: 0.1
B9: Gross margin % | D9: =IS!D9/IS!D7 | E9: =IS!E9/IS!E7 | F9: =IS!F9/IS!F7 | G9: 0.69 | H9: 0.69 | I9: 0.69 | J9: 0.69 | K9: 0.69
B10: R&D % of revenue | D10: =IS!D10/IS!D7 | E10: =IS!E10/IS!E7 | F10: =IS!F10/IS!F7 | G10: 0.115 | H10: 0.115 | I10: 0.115 | J10: 0.115 | K10: 0.115
B11: Sales & marketing % of revenue | D11: =IS!D11/IS!D7 | E11: =IS!E11/IS!E7 | F11: =IS!F11/IS!F7 | G11: 0.09 | H11: 0.09 | I11: 0.09 | J11: 0.09 | K11: 0.09
B12: G&A % of revenue | D12: =IS!D12/IS!D7 | E12: =IS!E12/IS!E7 | F12: =IS!F12/IS!F7 | G12: 0.024 | H12: 0.024 | I12: 0.024 | J12: 0.024 | K12: 0.024
B13: Effective tax rate % | D13: =IS!D18/IS!D17 | E13: =IS!E18/IS!E17 | F13: =IS!F18/IS!F17 | G13: 0.19 | H13: 0.19 | I13: 0.19 | J13: 0.19 | K13: 0.19
B14: Other income / (expense), net ($mm, held flat) | D14: =IS!D16 | E14: =IS!E16 | F14: =IS!F16 | G14: -500 | H14: -500 | I14: -500 | J14: -500 | K14: -500
B16: Balance Sheet Drivers
B17: Days sales outstanding (AR) | D17: =BS!D9/IS!D7*365 | E17: =BS!E9/IS!E7*365 | F17: =BS!F9/IS!F7*365 | G17: 88 | H17: 88 | I17: 88 | J17: 88 | K17: 88
B18: Inventory % of COGS | D18: =BS!D10/IS!D8 | E18: =BS!E10/IS!E8 | F18: =BS!F10/IS!F8 | G18: 0.0005 | H18: 0.0005 | I18: 0.0005 | J18: 0.0005 | K18: 0.0005
B19: Days payable outstanding (AP) | D19: =BS!D20/IS!D8*365 | E19: =BS!E20/IS!E8*365 | F19: =BS!F20/IS!F8*365 | G19: 110 | H19: 110 | I19: 110 | J19: 110 | K19: 110
B20: Accrued compensation % of total opex | D20: =BS!D21/(IS!D10+IS!D11+IS!D12) | E20: =BS!E21/(IS!E10+IS!E11+IS!E12) | F20: =BS!F21/(IS!F10+IS!F11+IS!F12) | G20: 0.2 | H20: 0.2 | I20: 0.2 | J20: 0.2 | K20: 0.2
B21: Total unearned revenue % of revenue | D21: =(BS!D22+BS!D27)/IS!D7 | E21: =(BS!E22+BS!E27)/IS!E7 | F21: =(BS!F22+BS!F27)/IS!F7 | G21: 0.185 | H21: 0.182 | I21: 0.179 | J21: 0.176 | K21: 0.173
B22: Short-term unearned revenue % of total unearned rev. | D22: =BS!D22/(BS!D22+BS!D27) | E22: =BS!E22/(BS!E22+BS!E27) | F22: =BS!F22/(BS!F22+BS!F27) | G22: 0.62 | H22: 0.62 | I22: 0.62 | J22: 0.62 | K22: 0.62
B23: Other current assets % of revenue | D23: =BS!D11/IS!D7 | E23: =BS!E11/IS!E7 | F23: =BS!F11/IS!F7 | G23: 0.07 | H23: 0.07 | I23: 0.07 | J23: 0.07 | K23: 0.07
B24: Other current liabilities % of revenue | D24: =BS!D24/IS!D7 | E24: =BS!E24/IS!E7 | F24: =BS!F24/IS!F7 | G24: 0.025 | H24: 0.025 | I24: 0.025 | J24: 0.025 | K24: 0.025
B25: Other LT assets % of revenue | D25: =BS!D16/IS!D7 | E25: =BS!E16/IS!E7 | F25: =BS!F16/IS!F7 | G25: 0.64 | H25: 0.63 | I25: 0.62 | J25: 0.61 | K25: 0.6
B26: Other LT liabilities % of revenue | D26: =BS!D28/IS!D7 | E26: =BS!E28/IS!E7 | F26: =BS!F28/IS!F7 | G26: 0.44 | H26: 0.43 | I26: 0.42 | J26: 0.41 | K26: 0.4
B27: Capex % of revenue | D27: n/a (see CF memo) | E27: n/a (see CF memo) | F27: n/a (see CF memo) | G27: 0.23 | H27: 0.21 | I27: 0.19 | J27: 0.17 | K27: 0.15
B28: Depreciation % of revenue | D28: n/a (see CF memo) | E28: n/a (see CF memo) | F28: n/a (see CF memo) | G28: 0.13 | H28: 0.13 | I28: 0.13 | J28: 0.13 | K28: 0.13
B29: Intangible asset amortization ($mm) | D29: n/a | E29: n/a | F29: n/a | G29: 2800 | H29: 2600 | I29: 2400 | J29: 2200 | K29: 2000
B31: Financing & Capital Structure Policy
B32: Dividend per share ($, annualized run-rate) | D32: n/a | E32: n/a | F32: 1.7824 | G32: =F32*(1+G33) | H32: =G32*(1+H33) | I32: =H32*(1+I33) | J32: =I32*(1+J33) | K32: =J32*(1+K33)
B33: Dividend per share growth % | D33: n/a | E33: n/a | F33: n/a | G33: 0.1 | H33: 0.09 | I33: 0.07 | J33: 0.05 | K33: 0.04
B34: Share buybacks ($mm/yr) | D34: n/a | E34: n/a | F34: n/a | G34: 20000 | H34: 22000 | I34: 24000 | J34: 26000 | K34: 28000
B35: Assumed avg. share price for buybacks ($) | D35: n/a | E35: n/a | F35: n/a | G35: 520 | H35: 560 | I35: 605 | J35: 650 | K35: 700
B36: Stock-based compensation % of revenue | D36: n/a | E36: n/a | F36: n/a | G36: 0.042 | H36: 0.042 | I36: 0.042 | J36: 0.042 | K36: 0.042
B37: SBC share dilution (% of shares/yr) | D37: n/a | E37: n/a | F37: n/a | G37: 0.005 | H37: 0.005 | I37: 0.005 | J37: 0.005 | K37: 0.005
B38: Option / stock plan proceeds ($mm/yr) | D38: n/a | E38: n/a | F38: n/a | G38: 900 | H38: 900 | I38: 900 | J38: 900 | K38: 900
B39: Scheduled LT debt maturities ($mm) | D39: n/a | E39: n/a | F39: n/a | G39: 3186 | H39: 2932 | I39: 2038 | J39: 1853 | K39: 1385
B40: Blended coupon rate on debt % | D40: n/a | E40: n/a | F40: n/a | G40: 0.0452 | H40: 0.0452 | I40: 0.0452 | J40: 0.0452 | K40: 0.0452
B41: Revolver interest rate % | D41: n/a | E41: n/a | F41: n/a | G41: 0.055 | H41: 0.055 | I41: 0.055 | J41: 0.055 | K41: 0.055
B42: Cash / ST investment interest income rate % | D42: n/a | E42: n/a | F42: n/a | G42: 0.04 | H42: 0.04 | I42: 0.04 | J42: 0.04 | K42: 0.04
B43: Minimum cash balance ($mm) | D43: n/a | E43: n/a | F43: n/a | G43: 15000 | H43: 15000 | I43: 15000 | J43: 15000 | K43: 15000
B45: Circularity convention: interest expense = beginning-of-period debt balance x coupon; interest income = beginning-of-period cash balance x rate; the revolver is sized as an end-of-period plug on the DebtSchedule tab. No iterative calculation is used or required.

Sheet IS
B2: Income Statement
B3: ($ in millions, except per-share data)
D5: FY2023A | E5: FY2024A | F5: FY2025A | G5: FY2026E | H5: FY2027E | I5: FY2028E | J5: FY2029E | K5: FY2030E
B7: Total revenue | D7: 211915 | E7: 245122 | F7: 281724 | G7: =F7*(1+Assumptions!G8) | H7: =G7*(1+Assumptions!H8) | I7: =H7*(1+Assumptions!I8) | J7: =I7*(1+Assumptions!J8) | K7: =J7*(1+Assumptions!K8)
B8: Cost of revenue | D8: 65863 | E8: 74114 | F8: 88159 | G8: =G7*(1-Assumptions!G9) | H8: =H7*(1-Assumptions!H9) | I8: =I7*(1-Assumptions!I9) | J8: =J7*(1-Assumptions!J9) | K8: =K7*(1-Assumptions!K9)
B9: Gross profit | D9: =D7-D8 | E9: =E7-E8 | F9: =F7-F8 | G9: =G7-G8 | H9: =H7-H8 | I9: =I7-I8 | J9: =J7-J8 | K9: =K7-K8
B10: Research & development | D10: 27195 | E10: 29510 | F10: 32500 | G10: =G7*Assumptions!G10 | H10: =H7*Assumptions!H10 | I10: =I7*Assumptions!I10 | J10: =J7*Assumptions!J10 | K10: =K7*Assumptions!K10
B11: Sales & marketing | D11: 22759 | E11: 24456 | F11: 25700 | G11: =G7*Assumptions!G11 | H11: =H7*Assumptions!H11 | I11: =I7*Assumptions!I11 | J11: =J7*Assumptions!J11 | K11: =K7*Assumptions!K11
B12: General & administrative | D12: 7575 | E12: 7609 | F12: 6837 | G12: =G7*Assumptions!G12 | H12: =H7*Assumptions!H12 | I12: =I7*Assumptions!I12 | J12: =J7*Assumptions!J12 | K12: =K7*Assumptions!K12
B13: Operating income | D13: =D9-D10-D11-D12 | E13: =E9-E10-E11-E12 | F13: =F9-F10-F11-F12 | G13: =G9-G10-G11-G12 | H13: =H9-H10-H11-H12 | I13: =I9-I10-I11-I12 | J13: =J9-J10-J11-J12 | K13: =K9-K10-K11-K12
B14: Interest income | D14: 2900 | E14: 3200 | F14: 3800 | G14: =DebtSchedule!G26 | H14: =DebtSchedule!H26 | I14: =DebtSchedule!I26 | J14: =DebtSchedule!J26 | K14: =DebtSchedule!K26
B15: Interest expense | D15: 1968 | E15: 2300 | F15: 2000 | G15: =DebtSchedule!G24 | H15: =DebtSchedule!H24 | I15: =DebtSchedule!I24 | J15: =DebtSchedule!J24 | K15: =DebtSchedule!K24
B16: Other income / (expense), net | D16: -144 | E16: -2850 | F16: -4455 | G16: =Assumptions!G14 | H16: =Assumptions!H14 | I16: =Assumptions!I14 | J16: =Assumptions!J14 | K16: =Assumptions!K14
B17: Pre-tax income | D17: =D13+D14-D15+D16 | E17: =E13+E14-E15+E16 | F17: =F13+F14-F15+F16 | G17: =G13+G14-G15+G16 | H17: =H13+H14-H15+H16 | I17: =I13+I14-I15+I16 | J17: =J13+J14-J15+J16 | K17: =K13+K14-K15+K16
B18: Income tax expense | D18: 16950 | E18: 19347 | F18: 24041 | G18: =G17*Assumptions!G13 | H18: =H17*Assumptions!H13 | I18: =I17*Assumptions!I13 | J18: =J17*Assumptions!J13 | K18: =K17*Assumptions!K13
B19: Net income | D19: =D17-D18 | E19: =E17-E18 | F19: =F17-F18 | G19: =G17-G18 | H19: =H17-H18 | I19: =I17-I18 | J19: =J17-J18 | K19: =K17-K18
B21: EPS memo
B22: Diluted shares outstanding, end of period (mm) | D22: 8097 | E22: 8024 | F22: 7462 | G22: =F22-Assumptions!G34/Assumptions!G35+Assumptions!G37*F22 | H22: =G22-Assumptions!H34/Assumptions!H35+Assumptions!H37*G22 | I22: =H22-Assumptions!I34/Assumptions!I35+Assumptions!I37*H22 | J22: =I22-Assumptions!J34/Assumptions!J35+Assumptions!J37*I22 | K22: =J22-Assumptions!K34/Assumptions!K35+Assumptions!K37*J22
B23: Weighted-avg diluted shares (mm) | D23: 8097 | E23: 8024 | F23: 7462 | G23: =AVERAGE(F22,G22) | H23: =AVERAGE(G22,H22) | I23: =AVERAGE(H22,I22) | J23: =AVERAGE(I22,J22) | K23: =AVERAGE(J22,K22)
B24: Diluted EPS ($) | D24: =D19/D23 | E24: =E19/E23 | F24: =F19/F23 | G24: =G19/G23 | H24: =H19/H23 | I24: =I19/I23 | J24: =J19/J23 | K24: =K19/K23

Sheet BS
B2: Balance Sheet
B3: ($ in millions)
D5: FY2023A | E5: FY2024A | F5: FY2025A | G5: FY2026E | H5: FY2027E | I5: FY2028E | J5: FY2029E | K5: FY2030E
B7: ASSETS
B8: Cash & equivalents + ST investments | D8: 111262 | E8: 75543 | F8: 94565 | G8: =CF!G42 | H8: =CF!H42 | I8: =CF!I42 | J8: =CF!J42 | K8: =CF!K42
B9: Accounts receivable | D9: 56900 | E9: 56924 | F9: 69905 | G9: =IS!G7/365*Assumptions!G17 | H9: =IS!H7/365*Assumptions!H17 | I9: =IS!I7/365*Assumptions!I17 | J9: =IS!J7/365*Assumptions!J17 | K9: =IS!K7/365*Assumptions!K17
B10: Inventory | D10: 30 | E10: 30 | F10: 30 | G10: =IS!G8*Assumptions!G18 | H10: =IS!H8*Assumptions!H18 | I10: =IS!I8*Assumptions!I18 | J10: =IS!J8*Assumptions!J18 | K10: =IS!K8*Assumptions!K18
B11: Other current assets | D11: 13000 | E11: 19500 | F11: 20000 | G11: =IS!G7*Assumptions!G23 | H11: =IS!H7*Assumptions!H23 | I11: =IS!I7*Assumptions!I23 | J11: =IS!J7*Assumptions!J23 | K11: =IS!K7*Assumptions!K23
B12: Total current assets | D12: =SUM(D8:D11) | E12: =SUM(E8:E11) | F12: =SUM(F8:F11) | G12: =SUM(G8:G11) | H12: =SUM(H8:H11) | I12: =SUM(I8:I11) | J12: =SUM(J8:J11) | K12: =SUM(K8:K11)
B13: Net property, plant & equipment | D13: 44800 | E13: 66300 | F13: 105000 | G13: =F13-CF!G29-CF!G14 | H13: =G13-CF!H29-CF!H14 | I13: =H13-CF!I29-CF!I14 | J13: =I13-CF!J29-CF!J14 | K13: =J13-CF!K29-CF!K14
B14: Goodwill | D14: 67886 | E14: 119220 | F14: 119509 | G14: =F14 | H14: =G14 | I14: =H14 | J14: =I14 | K14: =J14
B15: Intangible assets, net | D15: 9366 | E15: 27597 | F15: 28000 | G15: =F15-Assumptions!G29 | H15: =G15-Assumptions!H29 | I15: =H15-Assumptions!I29 | J15: =I15-Assumptions!J29 | K15: =J15-Assumptions!K29
B16: Other LT assets (incl. lease ROU, deferred tax, equity invest.) | D16: 108736 | E16: 147046 | F16: 181991 | G16: =IS!G7*Assumptions!G25 | H16: =IS!H7*Assumptions!H25 | I16: =IS!I7*Assumptions!I25 | J16: =IS!J7*Assumptions!J25 | K16: =IS!K7*Assumptions!K25
B17: TOTAL ASSETS | D17: =D12+SUM(D13:D16) | E17: =E12+SUM(E13:E16) | F17: =F12+SUM(F13:F16) | G17: =G12+SUM(G13:G16) | H17: =H12+SUM(H13:H16) | I17: =I12+SUM(I13:I16) | J17: =J12+SUM(J13:J16) | K17: =K12+SUM(K13:K16)
B19: LIABILITIES
B20: Accounts payable | D20: 18095 | E20: 21996 | F20: 27724 | G20: =IS!G8/365*Assumptions!G19 | H20: =IS!H8/365*Assumptions!H19 | I20: =IS!I8/365*Assumptions!I19 | J20: =IS!J8/365*Assumptions!J19 | K20: =IS!K8/365*Assumptions!K19
B21: Accrued compensation | D21: 9000 | E21: 11000 | F21: 13000 | G21: =(IS!G10+IS!G11+IS!G12)*Assumptions!G20 | H21: =(IS!H10+IS!H11+IS!H12)*Assumptions!H20 | I21: =(IS!I10+IS!I11+IS!I12)*Assumptions!I20 | J21: =(IS!J10+IS!J11+IS!J12)*Assumptions!J20 | K21: =(IS!K10+IS!K11+IS!K12)*Assumptions!K20
B22: Short-term unearned revenue | D22: 27600 | E22: 31400 | F22: 32000 | G22: =IS!G7*Assumptions!G21*Assumptions!G22 | H22: =IS!H7*Assumptions!H21*Assumptions!H22 | I22: =IS!I7*Assumptions!I21*Assumptions!I22 | J22: =IS!J7*Assumptions!J21*Assumptions!J22 | K22: =IS!K7*Assumptions!K21*Assumptions!K22
B23: Current portion of LTD + revolver borrowings | D23: 2600 | E23: 4400 | F23: 9227 | G23: =DebtSchedule!G11+DebtSchedule!G19 | H23: =DebtSchedule!H11+DebtSchedule!H19 | I23: =DebtSchedule!I11+DebtSchedule!I19 | J23: =DebtSchedule!J11+DebtSchedule!J19 | K23: =DebtSchedule!K11+DebtSchedule!K19
B24: Other current liabilities | D24: 6000 | E24: 6500 | F24: 7000 | G24: =IS!G7*Assumptions!G24 | H24: =IS!H7*Assumptions!H24 | I24: =IS!I7*Assumptions!I24 | J24: =IS!J7*Assumptions!J24 | K24: =IS!K7*Assumptions!K24
B25: Total current liabilities | D25: =SUM(D20:D24) | E25: =SUM(E20:E24) | F25: =SUM(F20:F24) | G25: =SUM(G20:G24) | H25: =SUM(H20:H24) | I25: =SUM(I20:I24) | J25: =SUM(J20:J24) | K25: =SUM(K20:K24)
B26: Long-term debt | D26: 55035 | E26: 56577 | F26: 40150 | G26: =DebtSchedule!G12 | H26: =DebtSchedule!H12 | I26: =DebtSchedule!I12 | J26: =DebtSchedule!J12 | K26: =DebtSchedule!K12
B27: Long-term unearned revenue | D27: 26000 | E27: 28800 | F27: 20000 | G27: =IS!G7*Assumptions!G21*(1-Assumptions!G22) | H27: =IS!H7*Assumptions!H21*(1-Assumptions!H22) | I27: =IS!I7*Assumptions!I21*(1-Assumptions!I22) | J27: =IS!J7*Assumptions!J21*(1-Assumptions!J22) | K27: =IS!K7*Assumptions!K21*(1-Assumptions!K22)
B28: Other LT liabilities (leases, deferred tax, pension, other) | D28: 61430 | E28: 83007 | F28: 126419 | G28: =IS!G7*Assumptions!G26 | H28: =IS!H7*Assumptions!H26 | I28: =IS!I7*Assumptions!I26 | J28: =IS!J7*Assumptions!J26 | K28: =IS!K7*Assumptions!K26
B29: Total liabilities | D29: =D25+SUM(D26:D28) | E29: =E25+SUM(E26:E28) | F29: =F25+SUM(F26:F28) | G29: =G25+SUM(G26:G28) | H29: =H25+SUM(H26:H28) | I29: =I25+SUM(I26:I28) | J29: =J25+SUM(J26:J28) | K29: =K25+SUM(K26:K28)
B31: EQUITY
B32: Common stock & APIC | D32: 38000 | E32: 46000 | F32: 54000 | G32: =F32+CF!G16+Assumptions!G38 | H32: =G32+CF!H16+Assumptions!H38 | I32: =H32+CF!I16+Assumptions!I38 | J32: =I32+CF!J16+Assumptions!J38 | K32: =J32+CF!K16+Assumptions!K38
B33: Retained earnings | D33: 165220 | E33: 220480 | F33: 280480 | G33: =F33+IS!G19+CF!G33+CF!G34 | H33: =G33+IS!H19+CF!H33+CF!H34 | I33: =H33+IS!I19+CF!I33+CF!I34 | J33: =I33+IS!J19+CF!J33+CF!J34 | K33: =J33+IS!K19+CF!K33+CF!K34
B34: Accumulated other comprehensive income / (loss) | D34: 3000 | E34: 2000 | F34: 9000 | G34: =F34 | H34: =G34 | I34: =H34 | J34: =I34 | K34: =J34
B35: Total equity | D35: =SUM(D32:D34) | E35: =SUM(E32:E34) | F35: =SUM(F32:F34) | G35: =SUM(G32:G34) | H35: =SUM(H32:H34) | I35: =SUM(I32:I34) | J35: =SUM(J32:J34) | K35: =SUM(K32:K34)
B37: TOTAL LIABILITIES + EQUITY | D37: =D29+D35 | E37: =E29+E35 | F37: =F29+F35 | G37: =G29+G35 | H37: =H29+H35 | I37: =I29+I35 | J37: =J29+J35 | K37: =K29+K35
B39: BALANCE CHECK (Total assets - Total L+E; must = 0.000) | D39: =ROUND(D17-D37,3) | E39: =ROUND(E17-E37,3) | F39: =ROUND(F17-F37,3) | G39: =ROUND(G17-G37,3) | H39: =ROUND(H17-H37,3) | I39: =ROUND(I17-I37,3) | J39: =ROUND(J17-J37,3) | K39: =ROUND(K17-K37,3)

Sheet CF
B2: Cash Flow Statement
B3: ($ in millions; indirect method; projection years fully built, historical years shown as a sourced memo per spec)
D5: FY2023A | E5: FY2024A | F5: FY2025A | G5: FY2026E | H5: FY2027E | I5: FY2028E | J5: FY2029E | K5: FY2030E
B7: Historical CF Memo (selected lines, source: 10-K; not part of the projected build)
B8: Operating cash flow | D8: 87580 | E8: 118550 | F8: 136160
B9: Capital expenditures | D9: -28110 | E9: -44480 | F9: -64550
B10: Financing cash flow | D10: -30000 | E10: -26200 | F10: -42400
B12: Operating Activities (indirect method) -- projection years
B13: Net income | G13: =IS!G19 | H13: =IS!H19 | I13: =IS!I19 | J13: =IS!J19 | K13: =IS!K19
B14: + Depreciation | G14: =IS!G7*Assumptions!G28 | H14: =IS!H7*Assumptions!H28 | I14: =IS!I7*Assumptions!I28 | J14: =IS!J7*Assumptions!J28 | K14: =IS!K7*Assumptions!K28
B15: + Intangible amortization | G15: =Assumptions!G29 | H15: =Assumptions!H29 | I15: =Assumptions!I29 | J15: =Assumptions!J29 | K15: =Assumptions!K29
B16: + Stock-based compensation | G16: =IS!G7*Assumptions!G36 | H16: =IS!H7*Assumptions!H36 | I16: =IS!I7*Assumptions!I36 | J16: =IS!J7*Assumptions!J36 | K16: =IS!K7*Assumptions!K36
B17: (-) Increase in accounts receivable | G17: =-(BS!G9-BS!F9) | H17: =-(BS!H9-BS!G9) | I17: =-(BS!I9-BS!H9) | J17: =-(BS!J9-BS!I9) | K17: =-(BS!K9-BS!J9)
B18: (-) Increase in inventory | G18: =-(BS!G10-BS!F10) | H18: =-(BS!H10-BS!G10) | I18: =-(BS!I10-BS!H10) | J18: =-(BS!J10-BS!I10) | K18: =-(BS!K10-BS!J10)
B19: + Increase in accounts payable | G19: =BS!G20-BS!F20 | H19: =BS!H20-BS!G20 | I19: =BS!I20-BS!H20 | J19: =BS!J20-BS!I20 | K19: =BS!K20-BS!J20
B20: + Increase in accrued compensation | G20: =BS!G21-BS!F21 | H20: =BS!H21-BS!G21 | I20: =BS!I21-BS!H21 | J20: =BS!J21-BS!I21 | K20: =BS!K21-BS!J21
B21: (-) Increase in other current assets | G21: =-(BS!G11-BS!F11) | H21: =-(BS!H11-BS!G11) | I21: =-(BS!I11-BS!H11) | J21: =-(BS!J11-BS!I11) | K21: =-(BS!K11-BS!J11)
B22: + Increase in other current liabilities | G22: =BS!G24-BS!F24 | H22: =BS!H24-BS!G24 | I22: =BS!I24-BS!H24 | J22: =BS!J24-BS!I24 | K22: =BS!K24-BS!J24
B23: + Increase in unearned revenue (ST + LT) | G23: =(BS!G22+BS!G27)-(BS!F22+BS!F27) | H23: =(BS!H22+BS!H27)-(BS!G22+BS!G27) | I23: =(BS!I22+BS!I27)-(BS!H22+BS!H27) | J23: =(BS!J22+BS!J27)-(BS!I22+BS!I27) | K23: =(BS!K22+BS!K27)-(BS!J22+BS!J27)
B24: + Increase in other LT liabilities | G24: =BS!G28-BS!F28 | H24: =BS!H28-BS!G28 | I24: =BS!I28-BS!H28 | J24: =BS!J28-BS!I28 | K24: =BS!K28-BS!J28
B25: (-) Increase in other LT assets | G25: =-(BS!G16-BS!F16) | H25: =-(BS!H16-BS!G16) | I25: =-(BS!I16-BS!H16) | J25: =-(BS!J16-BS!I16) | K25: =-(BS!K16-BS!J16)
B26: Cash flow from operations (CFO) | G26: =SUM(G13:G25) | H26: =SUM(H13:H25) | I26: =SUM(I13:I25) | J26: =SUM(J13:J25) | K26: =SUM(K13:K25)
B28: Investing Activities
B29: Capital expenditures | G29: =-IS!G7*Assumptions!G27 | H29: =-IS!H7*Assumptions!H27 | I29: =-IS!I7*Assumptions!I27 | J29: =-IS!J7*Assumptions!J27 | K29: =-IS!K7*Assumptions!K27
B30: Cash flow from investing (CFI) | G30: =G29 | H30: =H29 | I30: =I29 | J30: =J29 | K30: =K29
B32: Financing Activities
B33: Dividends paid | G33: =-Assumptions!G32*IS!G23 | H33: =-Assumptions!H32*IS!H23 | I33: =-Assumptions!I32*IS!I23 | J33: =-Assumptions!J32*IS!J23 | K33: =-Assumptions!K32*IS!K23
B34: Share buybacks | G34: =-Assumptions!G34 | H34: =-Assumptions!H34 | I34: =-Assumptions!I34 | J34: =-Assumptions!J34 | K34: =-Assumptions!K34
B35: Scheduled long-term debt repayment | G35: =-DebtSchedule!G9 | H35: =-DebtSchedule!H9 | I35: =-DebtSchedule!I9 | J35: =-DebtSchedule!J9 | K35: =-DebtSchedule!K9
B36: Revolver draw / (repayment) | G36: =DebtSchedule!G18 | H36: =DebtSchedule!H18 | I36: =DebtSchedule!I18 | J36: =DebtSchedule!J18 | K36: =DebtSchedule!K18
B37: Option / stock plan proceeds | G37: =Assumptions!G38 | H37: =Assumptions!H38 | I37: =Assumptions!I38 | J37: =Assumptions!J38 | K37: =Assumptions!K38
B38: Cash flow from financing (CFF) | G38: =SUM(G33:G37) | H38: =SUM(H33:H37) | I38: =SUM(I33:I37) | J38: =SUM(J33:J37) | K38: =SUM(K33:K37)
B40: Net change in cash | G40: =G26+G30+G38 | H40: =H26+H30+H38 | I40: =I26+I30+I38 | J40: =J26+J30+J38 | K40: =K26+K30+K38
B41: Beginning cash & ST investments | G41: =BS!F8 | H41: =BS!G8 | I41: =BS!H8 | J41: =BS!I8 | K41: =BS!J8
B42: Ending cash & ST investments | G42: =G41+G40 | H42: =H41+H40 | I42: =I41+I40 | J42: =J41+J40 | K42: =K41+K40

Sheet DebtSchedule
B2: Debt Schedule
B3: ($ in millions; interest on beginning-of-period balances -- no circularity)
D5: FY2023A | E5: FY2024A | F5: FY2025A | G5: FY2026E | H5: FY2027E | I5: FY2028E | J5: FY2029E | K5: FY2030E
B7: Long-Term Debt
B8: Opening balance (LT debt + current portion) | D8: n/a | E8: n/a | F8: n/a | G8: =F10 | H8: =G10 | I8: =H10 | J8: =I10 | K8: =J10
B9: Scheduled maturity / repayment | D9: n/a | E9: n/a | F9: n/a | G9: =Assumptions!G39 | H9: =Assumptions!H39 | I9: =Assumptions!I39 | J9: =Assumptions!J39 | K9: =Assumptions!K39
B10: Closing balance (total funded debt) | D10: 57635 | E10: 60977 | F10: 49377 | G10: =G8-G9 | H10: =H8-H9 | I10: =I8-I9 | J10: =J8-J9 | K10: =K8-K9
B11: Of which: current portion (next FY scheduled maturity) -> BS | D11: 2600 | E11: 4400 | F11: 9227 | G11: 2932 | H11: 2038 | I11: 1853 | J11: 1385 | K11: 1300
B12: Of which: long-term portion -> BS | D12: 55035 | E12: 56577 | F12: 40150 | G12: =G10-G11 | H12: =H10-H11 | I12: =I10-I11 | J12: =J10-J11 | K12: =K10-K11
B13: Interest expense (opening balance x coupon) | D13: n/a | E13: n/a | F13: n/a | G13: =G8*Assumptions!G40 | H13: =H8*Assumptions!H40 | I13: =I8*Assumptions!I40 | J13: =J8*Assumptions!J40 | K13: =K8*Assumptions!K40
B15: Revolver (period-end plug)
B16: Opening revolver balance | D16: n/a | E16: n/a | F16: n/a | G16: 0 | H16: =G19 | I16: =H19 | J16: =I19 | K16: =J19
B17: Cash available before revolver draw/(repay) | D17: n/a | E17: n/a | F17: n/a | G17: =BS!F8+CF!G26+CF!G30+CF!G33+CF!G34+CF!G35+CF!G37 | H17: =BS!G8+CF!H26+CF!H30+CF!H33+CF!H34+CF!H35+CF!H37 | I17: =BS!H8+CF!I26+CF!I30+CF!I33+CF!I34+CF!I35+CF!I37 | J17: =BS!I8+CF!J26+CF!J30+CF!J33+CF!J34+CF!J35+CF!J37 | K17: =BS!J8+CF!K26+CF!K30+CF!K33+CF!K34+CF!K35+CF!K37
B18: Revolver draw / (repay) | D18: n/a | E18: n/a | F18: n/a | G18: =MAX(0,Assumptions!G43-G17)-MIN(G16,MAX(0,G17-Assumptions!G43)) | H18: =MAX(0,Assumptions!H43-H17)-MIN(H16,MAX(0,H17-Assumptions!H43)) | I18: =MAX(0,Assumptions!I43-I17)-MIN(I16,MAX(0,I17-Assumptions!I43)) | J18: =MAX(0,Assumptions!J43-J17)-MIN(J16,MAX(0,J17-Assumptions!J43)) | K18: =MAX(0,Assumptions!K43-K17)-MIN(K16,MAX(0,K17-Assumptions!K43))
B19: Closing revolver balance | D19: 0 | E19: 0 | F19: 0 | G19: =G16+G18 | H19: =H16+H18 | I19: =I16+I18 | J19: =J16+J18 | K19: =K16+K18
B20: Interest expense on revolver (opening balance x rate) | D20: n/a | E20: n/a | F20: n/a | G20: =G16*Assumptions!G41 | H20: =H16*Assumptions!H41 | I20: =I16*Assumptions!I41 | J20: =J16*Assumptions!J41 | K20: =K16*Assumptions!K41
B22: Totals (-> IS)
B23: Total debt (LT + current portion + revolver) | D23: =D10+D19 | E23: =E10+E19 | F23: =F10+F19 | G23: =G10+G19 | H23: =H10+H19 | I23: =I10+I19 | J23: =J10+J19 | K23: =K10+K19
B24: Total interest expense (debt + revolver) -> IS | D24: n/a | E24: n/a | F24: n/a | G24: =G13+G20 | H24: =H13+H20 | I24: =I13+I20 | J24: =J13+J20 | K24: =K13+K20
B25: Beginning cash & ST investments (for interest income) | D25: n/a | E25: n/a | F25: n/a | G25: =BS!F8 | H25: =BS!G8 | I25: =BS!H8 | J25: =BS!I8 | K25: =BS!J8
B26: Interest income (beginning cash x rate) -> IS | D26: n/a | E26: n/a | F26: n/a | G26: =G25*Assumptions!G42 | H26: =H25*Assumptions!H42 | I26: =I25*Assumptions!I42 | J26: =J25*Assumptions!J42 | K26: =K25*Assumptions!K42
B29: Note: cash available before revolver already nets dividends, buybacks, and scheduled debt repayment (see CF cols 33-35, 37); the revolver draws only if available cash would fall below the minimum cash balance, and repays any outstanding balance first out of any cash surplus above minimum. MSFT's projected cash generation keeps the revolver undrawn in every year, which is the expected, realistic outcome.

Sheet Checks
B2: Consolidated Checks
B3: (all cells are live green links; every value must equal 0.000)
D5: FY2023A | E5: FY2024A | F5: FY2025A | G5: FY2026E | H5: FY2027E | I5: FY2028E | J5: FY2029E | K5: FY2030E
B8: BS balance check (Total assets - Total L+E) | D8: =BS!D39 | E8: =BS!E39 | F8: =BS!F39 | G8: =BS!G39 | H8: =BS!H39 | I8: =BS!I39 | J8: =BS!J39 | K8: =BS!K39
B9: CF ending cash = BS cash | D9: n/a (hist.) | E9: n/a (hist.) | F9: n/a (hist.) | G9: =ROUND(CF!G42-BS!G8,3) | H9: =ROUND(CF!H42-BS!H8,3) | I9: =ROUND(CF!I42-BS!I8,3) | J9: =ROUND(CF!J42-BS!J8,3) | K9: =ROUND(CF!K42-BS!K8,3)
B10: Retained earnings roll-forward tie | D10: n/a (hist.) | E10: n/a (hist.) | F10: n/a (hist.) | G10: =ROUND(BS!G33-(BS!F33+IS!G19+CF!G33+CF!G34),3) | H10: =ROUND(BS!H33-(BS!G33+IS!H19+CF!H33+CF!H34),3) | I10: =ROUND(BS!I33-(BS!H33+IS!I19+CF!I33+CF!I34),3) | J10: =ROUND(BS!J33-(BS!I33+IS!J19+CF!J33+CF!J34),3) | K10: =ROUND(BS!K33-(BS!J33+IS!K19+CF!K33+CF!K34),3)
B11: Debt schedule total debt = BS debt (LTD + ST debt incl. revolver) | D11: n/a (hist.) | E11: n/a (hist.) | F11: n/a (hist.) | G11: =ROUND(DebtSchedule!G23-(BS!G26+BS!G23),3) | H11: =ROUND(DebtSchedule!H23-(BS!H26+BS!H23),3) | I11: =ROUND(DebtSchedule!I23-(BS!I26+BS!I23),3) | J11: =ROUND(DebtSchedule!J23-(BS!J26+BS!J23),3) | K11: =ROUND(DebtSchedule!K23-(BS!K26+BS!K23),3)
B12: Interest expense: IS = DebtSchedule | D12: n/a (hist.) | E12: n/a (hist.) | F12: n/a (hist.) | G12: =ROUND(IS!G15-DebtSchedule!G24,3) | H12: =ROUND(IS!H15-DebtSchedule!H24,3) | I12: =ROUND(IS!I15-DebtSchedule!I24,3) | J12: =ROUND(IS!J15-DebtSchedule!J24,3) | K12: =ROUND(IS!K15-DebtSchedule!K24,3)
B15: ALL CHECKS PASS? | D15: =IF(AND(SUMPRODUCT(--ISERROR(D8:K12))=0,SUMPRODUCT(ABS(IF(ISNUMBER(D8:K12),D8:K12,0)))<0.01),"ALL CHECKS PASS","CHECK FAILED")
