Workbook

Sheet Cover
B2: ExxonMobil / Pioneer Natural Resources - All-Stock Merger Model
B3: ($ in millions, except per-share data and exchange ratio, unless noted)
B4: Deal: ExxonMobil (XOM) acquisition of Pioneer Natural Resources (PXD) - announced October 11, 2023; closed May 3, 2024
B5: Prepared by: Akul Veauli
B6: Date: August 23, 2026
B8: Model description: 100% stock-for-stock acquisition of Pioneer Natural Resources by ExxonMobil at a fixed exchange ratio of 2.3234 XOM shares per PXD share (no collar, no cash component at signing). The model builds standalone 3-year historical + 5-year projected P&Ls for both companies, the exchange-ratio share-issuance mechanics, a purchase price allocation that step s up PXD's oil & gas properties (not intangibles, per E&P deal convention) with an associated deferred tax liability, run-rate cost synergies phased in over the projection period, and pro-forma EPS accretion/(dilution) analysis. Because consideration is 100% stock, the Financing tab carries zero new debt and zero cash used by design; a %-cash toggle is retained purely as a live what-if lever exercised in Sensitivity Grid 2. See DealNotes below for a data-quality correction made to the source research memo's XOM share count.
B12: Color-code legend
B13: 123.4 (hardcoded input) | C13: Blue font / yellow fill = hardcoded assumption
B14: D8*D6 (same-sheet formula, shown as text) | C14: Black font = formula referencing same tab
B15: Assumptions!D8 (cross-tab link, shown as text) | C15: Green font = formula linking from another tab
B18: Table of contents
B19: Cover
B20: Assumptions
B21: Acquirer
B22: Target
B23: Synergies
B24: PPA-Financing
B25: ProForma
B26: Contribution
B27: Sensitivity
B29: Key outputs
B30: Exchange ratio (XOM per PXD share) | D30: =Assumptions!D8
B31: Implied offer price / PXD share | D31: =Assumptions!D9
B32: Premium to PXD unaffected price | D32: =Assumptions!D10
B33: Implied equity purchase price ($mm) | D33: =Assumptions!D13
B34: New XOM shares issued (mm) | D34: =Assumptions!D12
B35: FY2024E accretion/(dilution) % | D35: =ProForma!D18
B36: FY2028E accretion/(dilution) % | D36: =ProForma!H18
B37: PXD contribution vs. ownership delta (pts) | D37: =Contribution!E18
B39: Sources: XOM FY2021-2023 10-Ks (SEC EDGAR); PXD FY2021-2023 10-Ks; XOM/PXD joint press release (Oct 11, 2023); Form S-4/424B3 registration statement (Nov 2023); ExxonMobil FY2024 post-close investor materials (2024 synergy raise to >$3.0B/yr). D&A detail, precise effective tax rates, and the commodity price deck were not fully available in source filings extracted for this build; flagged estimates are noted in blue-input cells throughout.
B42: DealNotes - Data Corrections & Flagged Estimates
B43: SHARE-COUNT CORRECTION: source research memo (E8) estimated XOM FY2023 diluted shares at 1,600-1,650mm (implying EPS ~$22.50). XOM's actual reported GAAP diluted EPS was $8.89 on FY2023 net income of $36,010mm, which backs into ~4,049mm diluted shares -- consistent with XOM's real ~4.2-4.3bn share count. This build uses the EPS-consistent, corrected share counts (~4,049/4,203/4,275mm for FY23/22/21) since they are load-bearing for exchange-ratio share issuance and accretion math.
B44: OFFER PRICE: Assumptions tab uses the sourced XOM reference price of $110.41 (per press release) x the 2.3234 ratio, which computes to a $256.56 implied offer price and ~19.7% premium to PXD's $214.41 unaffected price. This is slightly above the commonly-cited headline framing of a ~$253 offer / ~18% premium, which likely used a trailing VWAP convention rather than the announcement-date spot close; both are within a normal band for this type of premium framing and the discrepancy is disclosed rather than forced to match the round-number headline.
B45: D&A / TAX RATE DETAIL: FY2021-2023 D&A and effective tax rate for both companies were not fully broken out in the source research memo. Acquirer/Target tabs use blue, flagged-estimate D&A and effective tax rate inputs reverse-solved to approximately reproduce each company's reported net income off of an assumed EBITDA margin; small residual variances vs. exact reported NI are expected and are a modeling simplification, not an error.
B46: SYNERGIES: modeled at the original $2.0B/yr run-rate announced Oct 2023 (phased in over the projection window) per the master synergies row; the 2024 upgrade to >$3.0B/yr is carried as a memo note only and is not the base case run-rate, to keep the model tied to deal-announcement-vintage assumptions used elsewhere in this build.
B47: COMMODITY DECK: per spec guidance, the operating projection is kept driver-based (blue revenue growth % and EBITDA margin %) rather than volume x price build-up; a flat WTI ~$75-80/bbl memo assumption is noted on the Acquirer/Target tabs as the qualitative backdrop for the growth/margin assumptions chosen.

Sheet Assumptions
B2: Assumptions
B3: ($ in millions, except per-share data and ratios)
B5: Deal Terms
B6: XOM reference share price at announcement (per press release) | D6: 110.41 | E6: Source: XOM/PXD joint press release, Oct 11, 2023
B7: PXD unaffected share price (Oct 5, 2023 close, pre-rumor) | D7: 214.41 | E7: Source: S-4/424B3 background of the merger section
B8: Exchange ratio (XOM shares per PXD share) | D8: 2.3234 | E8: THE key deal input -- fixed, no collar
B9: Implied offer price per PXD share | D9: =D8*D6
B10: Premium to PXD unaffected price | D10: =D9/D7-1 | E10: ~18-20% region; see Cover DealNotes on VWAP vs spot convention
B11: PXD fully diluted shares outstanding (mm) | D11: 233.6 | E11: Source: PXD FY2023 10-K cover / EPS note
B12: New XOM shares issued to PXD holders (mm) | D12: =D11*D8
B13: Implied equity purchase price ($mm) | D13: =D11*D9 | E13: ~$59.5B per deal announcement (~$59.1-59.5B depending on price convention)
B14: % cash consideration (base case; flex only in Sensitivity Grid 2) | D14: 0 | E14: Deal-actual: 100% stock, 0% cash
B15: % stock consideration | D15: =1-D14
B16: Cash consideration ($mm) | D16: =D13*D14
B17: Stock consideration ($mm) | D17: =D13*D15
B19: Financing (all-stock deal -- no new debt / cash used at base case)
B20: Cash from balance sheet used ($mm) | D20: 0
B21: New debt raised ($mm) | D21: =D16-D20
B22: Blended new-debt rate (illustrative, for %-cash what-if only) | D22: 0.0525 | E22: 2023 IG energy-sector proxy rate; not drawn at base case
B23: Foregone interest rate on cash used | D23: 0.05 | E23: 2023 money-market proxy rate
B24: Financing + advisory fees ($mm) | D24: 400 | E24: Flagged estimate -- advisory/legal fees for a deal of this size
B26: Purchase Price Allocation Inputs
B27: PXD book equity acquired ($mm) | D27: 14990 | E27: Flagged estimate, PXD FY2023 10-K stockholders' equity
B28: Existing PXD goodwill written off ($mm) | D28: 449 | E28: Flagged estimate, legacy Parsley/DoublePoint goodwill
B29: Excess purchase price over book (before step-ups) ($mm) | D29: =D13-D27+D28
B30: % of excess allocated to PP&E (oil & gas properties) step-up | D30: 0.6 | E30: E&P convention: step-up to proved/unproved properties, not intangibles
B31: PP&E (O&G properties) step-up ($mm) | D31: =D29*D30
B32: DTL toggle on step-up (1 = on, stock deal = carryover tax basis) | D32: 1
B33: Blended pro forma tax rate | D33: 0.245 | E33: Flagged estimate; used for DTL calc and ProForma tax line
B34: Deferred tax liability created on step-up ($mm) | D34: =D31*D33*D32
B35: Goodwill (residual) ($mm) | D35: =D29-D31+D34
B36: PP&E step-up amortization life (yrs, units-of-production proxy) | D36: 15
B37: Incremental DD&A from step-up ($mm/yr) | D37: =D31/D36
B39: Other
B40: Assume PXD existing debt continues post-close (1 = yes) | D40: 1
B41: Debt paydown sweep, % of pro forma NI (memo leverage only) | D41: 0.5
B42: EPS/accretion modeled FY2024E-FY2028E (5 yrs pro forma); historicals FY2021A-FY2023A on Acquirer/Target tabs. Interest computed on beginning-of-period balances to avoid circularity (no iterative calc), per master spec section 5.

Sheet Acquirer
B2: ExxonMobil (XOM) -- Standalone Projection
B3: ($ in millions, except per-share data)
D5: FY2021A | E5: FY2022A | F5: FY2023A | G5: FY2024E | H5: FY2025E | I5: FY2026E | J5: FY2027E | K5: FY2028E
B6: WTI crude oil price memo ($/bbl, flat-deck backdrop; not a direct revenue driver) | D6: 68 | E6: 94.9 | F6: 77.6 | G6: 78 | H6: 78 | I6: 78 | J6: 78 | K6: 78
B7: Revenue | D7: 285640 | E7: 413680 | F7: 344582 | G7: =F7*(1+G8) | H7: =G7*(1+H8) | I7: =H7*(1+I8) | J7: =I7*(1+J8) | K7: =J7*(1+K8)
B8: Revenue growth % | D8: n/a | E8: =E7/D7-1 | F8: =F7/E7-1 | G8: -0.03 | H8: 0.02 | I8: 0.02 | J8: 0.02 | K8: 0.02
B9: EBITDA margin % | D9: 0.17 | E9: 0.225 | F9: 0.2156 | G9: 0.21 | H9: 0.21 | I9: 0.21 | J9: 0.21 | K9: 0.21
B10: EBITDA | D10: =D7*D9 | E10: =E7*E9 | F10: =F7*F9 | G10: =G7*G9 | H10: =H7*H9 | I10: =I7*I9 | J10: =J7*J9 | K10: =K7*K9
B11: D&A | D11: 18500 | E11: 19000 | F11: 19600 | G11: =G7*G12 | H11: =H7*H12 | I11: =I7*I12 | J11: =J7*J12 | K11: =K7*K12
B12: D&A % of revenue (memo, hist; driver, proj) | D12: =D11/D7 | E12: =E11/E7 | F12: =F11/F7 | G12: 0.057 | H12: 0.057 | I12: 0.057 | J12: 0.057 | K12: 0.057
B13: EBIT | D13: =D10-D11 | E13: =E10-E11 | F13: =F10-F11 | G13: =G10-G11 | H13: =H10-H11 | I13: =I10-I11 | J13: =J10-J11 | K13: =K10-K11
B14: Interest expense | D14: 900 | E14: 700 | F14: 800 | G14: 800 | H14: 800 | I14: 800 | J14: 800 | K14: 800
B15: EBT | D15: =D13-D14 | E15: =E13-E14 | F15: =F13-F14 | G15: =G13-G14 | H15: =H13-H14 | I15: =I13-I14 | J15: =J13-J14 | K15: =K13-K14
B16: Tax rate % (effective; flagged estimate) | D16: 0.21 | E16: 0.24 | F16: 0.3316 | G16: 0.26 | H16: 0.26 | I16: 0.26 | J16: 0.26 | K16: 0.26
B17: Taxes | D17: =D15*D16 | E17: =E15*E16 | F17: =F15*F16 | G17: =G15*G16 | H17: =H15*H16 | I17: =I15*I16 | J17: =J15*J16 | K17: =K15*K16
B18: Net income | D18: =D15-D17 | E18: =E15-E17 | F18: =F15-F17 | G18: =G15-G17 | H18: =H15-H17 | I18: =I15-I17 | J18: =J15-J17 | K18: =K15-K17
B19: Diluted shares outstanding (mm) | D19: 4275 | E19: 4203 | F19: 4049 | G19: =F19*(1+G20) | H19: =G19*(1+H20) | I19: =H19*(1+I20) | J19: =I19*(1+J20) | K19: =J19*(1+K20)
B20: Share count growth % (buyback effect) | G20: -0.01 | H20: -0.01 | I20: -0.01 | J20: -0.01 | K20: -0.01
B21: Standalone diluted EPS ($) | D21: =D18/D19 | E21: =E18/E19 | F21: =F18/F19 | G21: =G18/G19 | H21: =H18/H19 | I21: =I18/I19 | J21: =J18/J19 | K21: =K18/K19
B23: Memo: net debt at FY2023A ($mm) | D23: 10100
B24: ExxonMobil historicals: revenue/EBITDA margin/D&A/interest are sourced or flagged estimates per Cover DealNotes; tax rate reverse-solved to approximate reported net income.

Sheet Target
B2: Pioneer Natural Resources (PXD) -- Standalone Projection
B3: ($ in millions, except per-share data)
D5: FY2021A | E5: FY2022A | F5: FY2023A | G5: FY2024E | H5: FY2025E | I5: FY2026E | J5: FY2027E | K5: FY2028E
B6: WTI crude oil price memo ($/bbl, flat-deck backdrop; not a direct revenue driver) | D6: 68 | E6: 94.9 | F6: 77.6 | G6: 78 | H6: 78 | I6: 78 | J6: 78 | K6: 78
B7: Revenue | D7: 14643 | E7: 24294 | F7: 19370 | G7: =F7*(1+G8) | H7: =G7*(1+H8) | I7: =H7*(1+I8) | J7: =I7*(1+J8) | K7: =J7*(1+K8)
B8: Revenue growth % | D8: n/a | E8: =E7/D7-1 | F8: =F7/E7-1 | G8: -0.05 | H8: 0.03 | I8: 0.03 | J8: 0.03 | K8: 0.03
B9: EBITDA margin % | D9: 0.4 | E9: 0.58 | F9: 0.52 | G9: 0.54 | H9: 0.54 | I9: 0.54 | J9: 0.54 | K9: 0.54
B10: EBITDA | D10: =D7*D9 | E10: =E7*E9 | F10: =F7*F9 | G10: =G7*G9 | H10: =H7*H9 | I10: =I7*I9 | J10: =J7*J9 | K10: =K7*K9
B11: D&A | D11: 2200 | E11: 2900 | F11: 3300 | G11: =G7*G12 | H11: =H7*H12 | I11: =I7*I12 | J11: =J7*J12 | K11: =K7*K12
B12: D&A % of revenue (memo, hist; driver, proj) | D12: =D11/D7 | E12: =E11/E7 | F12: =F11/F7 | G12: 0.15 | H12: 0.15 | I12: 0.15 | J12: 0.15 | K12: 0.15
B13: EBIT | D13: =D10-D11 | E13: =E10-E11 | F13: =F10-F11 | G13: =G10-G11 | H13: =H10-H11 | I13: =I10-I11 | J13: =J10-J11 | K13: =K10-K11
B14: Interest expense | D14: 230 | E14: 220 | F14: 230 | G14: 230 | H14: 230 | I14: 230 | J14: 230 | K14: 230
B15: EBT | D15: =D13-D14 | E15: =E13-E14 | F15: =F13-F14 | G15: =G13-G14 | H15: =H13-H14 | I15: =I13-I14 | J15: =J13-J14 | K15: =K13-K14
B16: Tax rate % (effective; flagged estimate) | D16: 0.382 | E16: 0.285 | F16: 0.251 | G16: 0.22 | H16: 0.22 | I16: 0.22 | J16: 0.22 | K16: 0.22
B17: Taxes | D17: =D15*D16 | E17: =E15*E16 | F17: =F15*F16 | G17: =G15*G16 | H17: =H15*H16 | I17: =I15*I16 | J17: =J15*J16 | K17: =K15*K16
B18: Net income | D18: =D15-D17 | E18: =E15-E17 | F18: =F15-F17 | G18: =G15-G17 | H18: =H15-H17 | I18: =I15-I17 | J18: =J15-J17 | K18: =K15-K17
B19: Diluted shares outstanding (mm) | D19: 247 | E19: 237 | F19: 233.6 | G19: =F19*(1+G20) | H19: =G19*(1+H20) | I19: =H19*(1+I20) | J19: =I19*(1+J20) | K19: =J19*(1+K20)
B20: Share count growth % (buyback effect) | G20: 0 | H20: 0 | I20: 0 | J20: 0 | K20: 0
B21: Standalone diluted EPS ($) | D21: =D18/D19 | E21: =E18/E19 | F21: =F18/F19 | G21: =G18/G19 | H21: =H18/H19 | I21: =I18/I19 | J21: =J18/J19 | K21: =K18/K19
B23: Memo: net debt at FY2023A ($mm) | D23: 4600
B24: Pioneer Natural Resources historicals: revenue/EBITDA margin/D&A/interest are sourced or flagged estimates per Cover DealNotes; tax rate reverse-solved to approximate reported net income.

Sheet Synergies
B2: Synergies
B3: ($ in millions)
D5: FY2024E | E5: FY2025E | F5: FY2026E | G5: FY2027E | H5: FY2028E
B6: Run-rate cost synergies ($mm) | D6: 2000 | E6: 2000 | F6: 2000 | G6: 2000 | H6: 2000
B7: Announced Oct 2023 run-rate; 2024 guidance raised to >$3.0B/yr (memo only, base case holds $2.0B run-rate for deal-vintage consistency -- see Cover DealNotes)
B8: Phase-in % of run-rate | D8: 0.4 | E8: 0.7 | F8: 0.9 | G8: 1 | H8: 1
B9: Cost synergies realized ($mm) | D9: =D6*D8 | E9: =E6*E8 | F9: =F6*F8 | G9: =G6*G8 | H9: =H6*H8
B10: Revenue synergies ($mm) | D10: 0 | E10: 0 | F10: 0 | G10: 0 | H10: 0
B11: Integration costs (one-time, expensed) ($mm) | D11: 300 | E11: 150 | F11: 0 | G11: 0 | H11: 0
B12: Pre-tax net synergy impact ($mm) | D12: =D9+D10-D11 | E12: =E9+E10-E11 | F12: =F9+F10-F11 | G12: =G9+G10-G11 | H12: =H9+H10-H11
B13: After-tax net synergy impact ($mm) | D13: =D12*(1-Assumptions!$D$33) | E13: =E12*(1-Assumptions!$D$33) | F13: =F12*(1-Assumptions!$D$33) | G13: =G12*(1-Assumptions!$D$33) | H13: =H12*(1-Assumptions!$D$33)

Sheet PPA-Financing
B2: PPA-Financing
B3: ($ in millions)
B5: Sources & Uses (at close, all-stock)
B6: Sources:
B7: New debt raised | D7: =Assumptions!D21
B8: Cash from balance sheet used | D8: =Assumptions!D20
B9: XOM stock issued to PXD holders | D9: =Assumptions!D17
B10: Cash used to pay fees (funded by XOM balance sheet) | D10: =Assumptions!D24
B11: Total sources | D11: =SUM(D7:D10)
B13: Uses:
B14: Equity purchase price | D14: =Assumptions!D13
B15: Financing + advisory fees | D15: =Assumptions!D24
B16: Total uses | D16: =SUM(D14:D15)
B17: Check (Sources - Uses, must = 0.000) | D17: =ROUND(D11-D16,3)
B20: Goodwill Build (waterfall)
B21: Equity purchase price | D21: =Assumptions!D13
B22: Less: PXD book equity acquired | D22: =-Assumptions!D27
B23: Plus: existing PXD goodwill written off | D23: =Assumptions!D28
B24: Less: PP&E (O&G properties) step-up | D24: =-Assumptions!D31
B25: Plus: deferred tax liability created | D25: =Assumptions!D34
B26: New goodwill | D26: =SUM(D21:D25)
B27: Check vs. Assumptions goodwill row (must = 0.000) | D27: =ROUND(D26-Assumptions!D35,3)
B30: Financing Effects / Year
D31: FY2024E | E31: FY2025E | F31: FY2026E | G31: FY2027E | H31: FY2028E
B32: New debt interest expense | D32: =Assumptions!$D$21*Assumptions!$D$22 | E32: =Assumptions!$D$21*Assumptions!$D$22 | F32: =Assumptions!$D$21*Assumptions!$D$22 | G32: =Assumptions!$D$21*Assumptions!$D$22 | H32: =Assumptions!$D$21*Assumptions!$D$22
B33: Foregone interest on cash used | D33: =Assumptions!$D$20*Assumptions!$D$23 | E33: =Assumptions!$D$20*Assumptions!$D$23 | F33: =Assumptions!$D$20*Assumptions!$D$23 | G33: =Assumptions!$D$20*Assumptions!$D$23 | H33: =Assumptions!$D$20*Assumptions!$D$23
B34: Incremental PP&E (O&G) DD&A from step-up | D34: =Assumptions!$D$37 | E34: =Assumptions!$D$37 | F34: =Assumptions!$D$37 | G34: =Assumptions!$D$37 | H34: =Assumptions!$D$37
B35: Financing/advisory fees are expensed at close (no debt tenor to amortize over in the all-stock base case); n/a in the %-cash what-if since new debt there is also modeled as a Grid-2-only construct.

Sheet ProForma
B2: ProForma
B3: ($ in millions, except per-share data)
D5: FY2024E | E5: FY2025E | F5: FY2026E | G5: FY2027E | H5: FY2028E
B6: Pro forma revenue | D6: =Acquirer!G7+Target!G7+Synergies!D10 | E6: =Acquirer!H7+Target!H7+Synergies!E10 | F6: =Acquirer!I7+Target!I7+Synergies!F10 | G6: =Acquirer!J7+Target!J7+Synergies!G10 | H6: =Acquirer!K7+Target!K7+Synergies!H10
B7: Pro forma EBITDA | D7: =Acquirer!G10+Target!G10+Synergies!D9-Synergies!D11 | E7: =Acquirer!H10+Target!H10+Synergies!E9-Synergies!E11 | F7: =Acquirer!I10+Target!I10+Synergies!F9-Synergies!F11 | G7: =Acquirer!J10+Target!J10+Synergies!G9-Synergies!G11 | H7: =Acquirer!K10+Target!K10+Synergies!H9-Synergies!H11
B8: Combined D&A + incremental PP&E step-up DD&A | D8: =Acquirer!G11+Target!G11+'PPA-Financing'!$D$34 | E8: =Acquirer!H11+Target!H11+'PPA-Financing'!$D$34 | F8: =Acquirer!I11+Target!I11+'PPA-Financing'!$D$34 | G8: =Acquirer!J11+Target!J11+'PPA-Financing'!$D$34 | H8: =Acquirer!K11+Target!K11+'PPA-Financing'!$D$34
B9: Pro forma EBIT | D9: =D7-D8 | E9: =E7-E8 | F9: =F7-F8 | G9: =G7-G8 | H9: =H7-H8
B10: Interest expense (acquirer + target [toggle] + new debt + foregone cash yield) | D10: =Acquirer!G14+Target!G14*Assumptions!$D$40+'PPA-Financing'!$D$32+'PPA-Financing'!$D$33 | E10: =Acquirer!H14+Target!H14*Assumptions!$D$40+'PPA-Financing'!$D$32+'PPA-Financing'!$D$33 | F10: =Acquirer!I14+Target!I14*Assumptions!$D$40+'PPA-Financing'!$D$32+'PPA-Financing'!$D$33 | G10: =Acquirer!J14+Target!J14*Assumptions!$D$40+'PPA-Financing'!$D$32+'PPA-Financing'!$D$33 | H10: =Acquirer!K14+Target!K14*Assumptions!$D$40+'PPA-Financing'!$D$32+'PPA-Financing'!$D$33
B11: Pro forma EBT | D11: =D9-D10 | E11: =E9-E10 | F11: =F9-F10 | G11: =G9-G10 | H11: =H9-H10
B12: Taxes @ blended rate | D12: =D11*Assumptions!$D$33 | E12: =E11*Assumptions!$D$33 | F12: =F11*Assumptions!$D$33 | G12: =G11*Assumptions!$D$33 | H12: =H11*Assumptions!$D$33
B13: Pro forma net income | D13: =D11-D12 | E13: =E11-E12 | F13: =F11-F12 | G13: =G11-G12 | H13: =H11-H12
B14: Pro forma diluted shares (acquirer standalone + new shares issued) | D14: =Acquirer!G19+Assumptions!$D$12 | E14: =Acquirer!H19+Assumptions!$D$12 | F14: =Acquirer!I19+Assumptions!$D$12 | G14: =Acquirer!J19+Assumptions!$D$12 | H14: =Acquirer!K19+Assumptions!$D$12
B15: Pro forma EPS ($) | D15: =D13/D14 | E15: =E13/E14 | F15: =F13/F14 | G15: =G13/G14 | H15: =H13/H14
B16: Acquirer (XOM) standalone EPS ($) | D16: =Acquirer!G21 | E16: =Acquirer!H21 | F16: =Acquirer!I21 | G16: =Acquirer!J21 | H16: =Acquirer!K21
B17: Accretion / (dilution), $ per share | D17: =D15-D16 | E17: =E15-E16 | F17: =F15-F16 | G17: =G15-G16 | H17: =H15-H16
B18: Accretion / (dilution), % | D18: =D15/D16-1 | E18: =E15/E16-1 | F18: =F15/F16-1 | G18: =G15/G16-1 | H18: =H15/H16-1
B20: Breakeven Synergies (Yr-1, FY2024E)
B21: Breakeven run-rate cost synergies, pre-tax ($mm) | D21: =(D16*D14 - (D13-Synergies!D9*(1-Assumptions!$D$33))) / ((1-Assumptions!$D$33)*Synergies!D8)
B22: Cross-check: plug breakeven into accretion formula (must = 0.000) | D22: =ROUND((( D13-Synergies!D9*(1-Assumptions!$D$33)+D21*(1-Assumptions!$D$33)*Synergies!D8 )/D14) / D16 - 1,3)
B24: Memo: Pro Forma Leverage (simple FCF debt paydown sweep)
D25: FY2024E | E25: FY2025E | F25: FY2026E | G25: FY2027E | H25: FY2028E
B26: Opening net debt (XOM + PXD standalone, no new debt) | D26: =Acquirer!$D$23+Target!$D$23+Assumptions!$D$21 | E26: =D28 | F26: =E28 | G26: =F28 | H26: =G28
B27: Debt paydown (sweep % of pro forma NI, floored at opening balance) | D27: =MAX(0,MIN(D13*Assumptions!$D$41,D26)) | E27: =MAX(0,MIN(E13*Assumptions!$D$41,E26)) | F27: =MAX(0,MIN(F13*Assumptions!$D$41,F26)) | G27: =MAX(0,MIN(G13*Assumptions!$D$41,G26)) | H27: =MAX(0,MIN(H13*Assumptions!$D$41,H26))
B28: Closing net debt | D28: =D26-D27 | E28: =E26-E27 | F28: =F26-F27 | G28: =G26-G27 | H28: =H26-H27
B29: Net debt / EBITDA | D29: =IFERROR(D28/D7,"n.m.") | E29: =IFERROR(E28/E7,"n.m.") | F29: =IFERROR(F28/F7,"n.m.") | G29: =IFERROR(G28/G7,"n.m.") | H29: =IFERROR(H28/H7,"n.m.")

Sheet Contribution
B2: Contribution Analysis
B3: ($ in millions; FY2023A basis, last full year pre-close)
D5: Acquirer (XOM) | E5: Target (PXD) | F5: Combined
B6: Revenue | D6: =Acquirer!F7 | E6: =Target!F7 | F6: =D6+E6
B7: % of combined (Revenue) | D7: =D6/F6 | E7: =E6/F6
B8: EBITDA | D8: =Acquirer!F10 | E8: =Target!F10 | F8: =D8+E8
B9: % of combined (EBITDA) | D9: =D8/F8 | E9: =E8/F8
B10: EBIT | D10: =Acquirer!F13 | E10: =Target!F13 | F10: =D10+E10
B11: % of combined (EBIT) | D11: =D10/F10 | E11: =E10/F10
B12: Net income | D12: =Acquirer!F18 | E12: =Target!F18 | F12: =D12+E12
B13: % of combined (Net income) | D13: =D12/F12 | E13: =E12/F12
B15: Ownership vs. Earnings Contribution
B16: Pro forma ownership % | D16: =Acquirer!F19/(Acquirer!F19+Assumptions!$D$12) | E16: =Assumptions!$D$12/(Acquirer!F19+Assumptions!$D$12)
B17: FY2023A net income contribution % | D17: =D12/F12 | E17: =E12/F12
B18: Contribution vs. ownership delta (pts) | D18: =D17-D16 | E18: =E17-E16 | G18: PXD earnings contribution vs. its ~12-13% pro forma ownership stake -- the star output of this tab
B20: PXD contributes disproportionately more FY2023A net income than its pro forma share-ownership stake would imply, since PXD's E&P earnings yield exceeded XOM's at signing -- consistent with the modest EPS accretion shown on the ProForma tab.

Sheet Sensitivity
B2: Sensitivity
B3: Algebraic re-derivation per cell (no Excel Data Tables) -- master spec section 4
B5: Grid 1: Exchange Ratio x Run-Rate Synergies -> FY2024E Accretion/(Dilution) %
B6: Helper columns compute, per exchange-ratio row: new shares, equity purchase price, PF NI, PF EPS.
C7: Ratio | D7: New shares | E7: Equity PP ($mm)
C8: 2.0234 | D8: =Assumptions!$D$11*C8 | E8: =Assumptions!$D$11*C8*Assumptions!$D$6
C9: 2.1734 | D9: =Assumptions!$D$11*C9 | E9: =Assumptions!$D$11*C9*Assumptions!$D$6
C10: 2.3234 | D10: =Assumptions!$D$11*C10 | E10: =Assumptions!$D$11*C10*Assumptions!$D$6
C11: 2.4734 | D11: =Assumptions!$D$11*C11 | E11: =Assumptions!$D$11*C11*Assumptions!$D$6
C12: 2.6234 | D12: =Assumptions!$D$11*C12 | E12: =Assumptions!$D$11*C12*Assumptions!$D$6
B14: Yr1 accretion % grid (rows = ratio; cols = synergy run-rate $bn)
C15: =D18 | D15: 0 | E15: 1 | F15: 2 | G15: 3 | H15: 4
C16: =C8 | D16: =((Acquirer!$G$15+Target!$G$15+D$15*1000*Synergies!$D$8-Synergies!$D$11-Assumptions!$D$37-'PPA-Financing'!$D$32-'PPA-Financing'!$D$33)*(1-Assumptions!$D$33)/(Acquirer!$G$19+$D$8))/Acquirer!$G$21-1 | E16: =((Acquirer!$G$15+Target!$G$15+E$15*1000*Synergies!$D$8-Synergies!$D$11-Assumptions!$D$37-'PPA-Financing'!$D$32-'PPA-Financing'!$D$33)*(1-Assumptions!$D$33)/(Acquirer!$G$19+$D$8))/Acquirer!$G$21-1 | F16: =((Acquirer!$G$15+Target!$G$15+F$15*1000*Synergies!$D$8-Synergies!$D$11-Assumptions!$D$37-'PPA-Financing'!$D$32-'PPA-Financing'!$D$33)*(1-Assumptions!$D$33)/(Acquirer!$G$19+$D$8))/Acquirer!$G$21-1 | G16: =((Acquirer!$G$15+Target!$G$15+G$15*1000*Synergies!$D$8-Synergies!$D$11-Assumptions!$D$37-'PPA-Financing'!$D$32-'PPA-Financing'!$D$33)*(1-Assumptions!$D$33)/(Acquirer!$G$19+$D$8))/Acquirer!$G$21-1 | H16: =((Acquirer!$G$15+Target!$G$15+H$15*1000*Synergies!$D$8-Synergies!$D$11-Assumptions!$D$37-'PPA-Financing'!$D$32-'PPA-Financing'!$D$33)*(1-Assumptions!$D$33)/(Acquirer!$G$19+$D$8))/Acquirer!$G$21-1
C17: =C9 | D17: =((Acquirer!$G$15+Target!$G$15+D$15*1000*Synergies!$D$8-Synergies!$D$11-Assumptions!$D$37-'PPA-Financing'!$D$32-'PPA-Financing'!$D$33)*(1-Assumptions!$D$33)/(Acquirer!$G$19+$D$9))/Acquirer!$G$21-1 | E17: =((Acquirer!$G$15+Target!$G$15+E$15*1000*Synergies!$D$8-Synergies!$D$11-Assumptions!$D$37-'PPA-Financing'!$D$32-'PPA-Financing'!$D$33)*(1-Assumptions!$D$33)/(Acquirer!$G$19+$D$9))/Acquirer!$G$21-1 | F17: =((Acquirer!$G$15+Target!$G$15+F$15*1000*Synergies!$D$8-Synergies!$D$11-Assumptions!$D$37-'PPA-Financing'!$D$32-'PPA-Financing'!$D$33)*(1-Assumptions!$D$33)/(Acquirer!$G$19+$D$9))/Acquirer!$G$21-1 | G17: =((Acquirer!$G$15+Target!$G$15+G$15*1000*Synergies!$D$8-Synergies!$D$11-Assumptions!$D$37-'PPA-Financing'!$D$32-'PPA-Financing'!$D$33)*(1-Assumptions!$D$33)/(Acquirer!$G$19+$D$9))/Acquirer!$G$21-1 | H17: =((Acquirer!$G$15+Target!$G$15+H$15*1000*Synergies!$D$8-Synergies!$D$11-Assumptions!$D$37-'PPA-Financing'!$D$32-'PPA-Financing'!$D$33)*(1-Assumptions!$D$33)/(Acquirer!$G$19+$D$9))/Acquirer!$G$21-1
C18: =C10 | D18: =((Acquirer!$G$15+Target!$G$15+D$15*1000*Synergies!$D$8-Synergies!$D$11-Assumptions!$D$37-'PPA-Financing'!$D$32-'PPA-Financing'!$D$33)*(1-Assumptions!$D$33)/(Acquirer!$G$19+$D$10))/Acquirer!$G$21-1 | E18: =((Acquirer!$G$15+Target!$G$15+E$15*1000*Synergies!$D$8-Synergies!$D$11-Assumptions!$D$37-'PPA-Financing'!$D$32-'PPA-Financing'!$D$33)*(1-Assumptions!$D$33)/(Acquirer!$G$19+$D$10))/Acquirer!$G$21-1 | F18: =((Acquirer!$G$15+Target!$G$15+F$15*1000*Synergies!$D$8-Synergies!$D$11-Assumptions!$D$37-'PPA-Financing'!$D$32-'PPA-Financing'!$D$33)*(1-Assumptions!$D$33)/(Acquirer!$G$19+$D$10))/Acquirer!$G$21-1 | G18: =((Acquirer!$G$15+Target!$G$15+G$15*1000*Synergies!$D$8-Synergies!$D$11-Assumptions!$D$37-'PPA-Financing'!$D$32-'PPA-Financing'!$D$33)*(1-Assumptions!$D$33)/(Acquirer!$G$19+$D$10))/Acquirer!$G$21-1 | H18: =((Acquirer!$G$15+Target!$G$15+H$15*1000*Synergies!$D$8-Synergies!$D$11-Assumptions!$D$37-'PPA-Financing'!$D$32-'PPA-Financing'!$D$33)*(1-Assumptions!$D$33)/(Acquirer!$G$19+$D$10))/Acquirer!$G$21-1
C19: =C11 | D19: =((Acquirer!$G$15+Target!$G$15+D$15*1000*Synergies!$D$8-Synergies!$D$11-Assumptions!$D$37-'PPA-Financing'!$D$32-'PPA-Financing'!$D$33)*(1-Assumptions!$D$33)/(Acquirer!$G$19+$D$11))/Acquirer!$G$21-1 | E19: =((Acquirer!$G$15+Target!$G$15+E$15*1000*Synergies!$D$8-Synergies!$D$11-Assumptions!$D$37-'PPA-Financing'!$D$32-'PPA-Financing'!$D$33)*(1-Assumptions!$D$33)/(Acquirer!$G$19+$D$11))/Acquirer!$G$21-1 | F19: =((Acquirer!$G$15+Target!$G$15+F$15*1000*Synergies!$D$8-Synergies!$D$11-Assumptions!$D$37-'PPA-Financing'!$D$32-'PPA-Financing'!$D$33)*(1-Assumptions!$D$33)/(Acquirer!$G$19+$D$11))/Acquirer!$G$21-1 | G19: =((Acquirer!$G$15+Target!$G$15+G$15*1000*Synergies!$D$8-Synergies!$D$11-Assumptions!$D$37-'PPA-Financing'!$D$32-'PPA-Financing'!$D$33)*(1-Assumptions!$D$33)/(Acquirer!$G$19+$D$11))/Acquirer!$G$21-1 | H19: =((Acquirer!$G$15+Target!$G$15+H$15*1000*Synergies!$D$8-Synergies!$D$11-Assumptions!$D$37-'PPA-Financing'!$D$32-'PPA-Financing'!$D$33)*(1-Assumptions!$D$33)/(Acquirer!$G$19+$D$11))/Acquirer!$G$21-1
C20: =C12 | D20: =((Acquirer!$G$15+Target!$G$15+D$15*1000*Synergies!$D$8-Synergies!$D$11-Assumptions!$D$37-'PPA-Financing'!$D$32-'PPA-Financing'!$D$33)*(1-Assumptions!$D$33)/(Acquirer!$G$19+$D$12))/Acquirer!$G$21-1 | E20: =((Acquirer!$G$15+Target!$G$15+E$15*1000*Synergies!$D$8-Synergies!$D$11-Assumptions!$D$37-'PPA-Financing'!$D$32-'PPA-Financing'!$D$33)*(1-Assumptions!$D$33)/(Acquirer!$G$19+$D$12))/Acquirer!$G$21-1 | F20: =((Acquirer!$G$15+Target!$G$15+F$15*1000*Synergies!$D$8-Synergies!$D$11-Assumptions!$D$37-'PPA-Financing'!$D$32-'PPA-Financing'!$D$33)*(1-Assumptions!$D$33)/(Acquirer!$G$19+$D$12))/Acquirer!$G$21-1 | G20: =((Acquirer!$G$15+Target!$G$15+G$15*1000*Synergies!$D$8-Synergies!$D$11-Assumptions!$D$37-'PPA-Financing'!$D$32-'PPA-Financing'!$D$33)*(1-Assumptions!$D$33)/(Acquirer!$G$19+$D$12))/Acquirer!$G$21-1 | H20: =((Acquirer!$G$15+Target!$G$15+H$15*1000*Synergies!$D$8-Synergies!$D$11-Assumptions!$D$37-'PPA-Financing'!$D$32-'PPA-Financing'!$D$33)*(1-Assumptions!$D$33)/(Acquirer!$G$19+$D$12))/Acquirer!$G$21-1
B22: Check: center cell (ratio=2.3234, syn=$2.0B) vs. ProForma FY2024E accretion (must = 0.000) | D22: =ROUND(F18-ProForma!D18,3)
B25: Grid 2: % Cash Consideration x Run-Rate Synergies -> FY2024E Accretion/(Dilution) %
B26: What-if only: base deal is 100% stock. Cash portion assumed 100% debt-funded at the blended rate.
C27: =D18 | D27: 0 | E27: 1 | F27: 2 | G27: 3 | H27: 4
C28: 0 | D28: =((Acquirer!$G$15+Target!$G$15+D$27*1000*Synergies!$D$8-Synergies!$D$11-Assumptions!$D$37-(Assumptions!$D$13*$C28)*Assumptions!$D$22)*(1-Assumptions!$D$33)/(Acquirer!$G$19+(Assumptions!$D$13*(1-$C28)/Assumptions!$D$6)))/Acquirer!$G$21-1 | E28: =((Acquirer!$G$15+Target!$G$15+E$27*1000*Synergies!$D$8-Synergies!$D$11-Assumptions!$D$37-(Assumptions!$D$13*$C28)*Assumptions!$D$22)*(1-Assumptions!$D$33)/(Acquirer!$G$19+(Assumptions!$D$13*(1-$C28)/Assumptions!$D$6)))/Acquirer!$G$21-1 | F28: =((Acquirer!$G$15+Target!$G$15+F$27*1000*Synergies!$D$8-Synergies!$D$11-Assumptions!$D$37-(Assumptions!$D$13*$C28)*Assumptions!$D$22)*(1-Assumptions!$D$33)/(Acquirer!$G$19+(Assumptions!$D$13*(1-$C28)/Assumptions!$D$6)))/Acquirer!$G$21-1 | G28: =((Acquirer!$G$15+Target!$G$15+G$27*1000*Synergies!$D$8-Synergies!$D$11-Assumptions!$D$37-(Assumptions!$D$13*$C28)*Assumptions!$D$22)*(1-Assumptions!$D$33)/(Acquirer!$G$19+(Assumptions!$D$13*(1-$C28)/Assumptions!$D$6)))/Acquirer!$G$21-1 | H28: =((Acquirer!$G$15+Target!$G$15+H$27*1000*Synergies!$D$8-Synergies!$D$11-Assumptions!$D$37-(Assumptions!$D$13*$C28)*Assumptions!$D$22)*(1-Assumptions!$D$33)/(Acquirer!$G$19+(Assumptions!$D$13*(1-$C28)/Assumptions!$D$6)))/Acquirer!$G$21-1
C29: 0.25 | D29: =((Acquirer!$G$15+Target!$G$15+D$27*1000*Synergies!$D$8-Synergies!$D$11-Assumptions!$D$37-(Assumptions!$D$13*$C29)*Assumptions!$D$22)*(1-Assumptions!$D$33)/(Acquirer!$G$19+(Assumptions!$D$13*(1-$C29)/Assumptions!$D$6)))/Acquirer!$G$21-1 | E29: =((Acquirer!$G$15+Target!$G$15+E$27*1000*Synergies!$D$8-Synergies!$D$11-Assumptions!$D$37-(Assumptions!$D$13*$C29)*Assumptions!$D$22)*(1-Assumptions!$D$33)/(Acquirer!$G$19+(Assumptions!$D$13*(1-$C29)/Assumptions!$D$6)))/Acquirer!$G$21-1 | F29: =((Acquirer!$G$15+Target!$G$15+F$27*1000*Synergies!$D$8-Synergies!$D$11-Assumptions!$D$37-(Assumptions!$D$13*$C29)*Assumptions!$D$22)*(1-Assumptions!$D$33)/(Acquirer!$G$19+(Assumptions!$D$13*(1-$C29)/Assumptions!$D$6)))/Acquirer!$G$21-1 | G29: =((Acquirer!$G$15+Target!$G$15+G$27*1000*Synergies!$D$8-Synergies!$D$11-Assumptions!$D$37-(Assumptions!$D$13*$C29)*Assumptions!$D$22)*(1-Assumptions!$D$33)/(Acquirer!$G$19+(Assumptions!$D$13*(1-$C29)/Assumptions!$D$6)))/Acquirer!$G$21-1 | H29: =((Acquirer!$G$15+Target!$G$15+H$27*1000*Synergies!$D$8-Synergies!$D$11-Assumptions!$D$37-(Assumptions!$D$13*$C29)*Assumptions!$D$22)*(1-Assumptions!$D$33)/(Acquirer!$G$19+(Assumptions!$D$13*(1-$C29)/Assumptions!$D$6)))/Acquirer!$G$21-1
C30: 0.5 | D30: =((Acquirer!$G$15+Target!$G$15+D$27*1000*Synergies!$D$8-Synergies!$D$11-Assumptions!$D$37-(Assumptions!$D$13*$C30)*Assumptions!$D$22)*(1-Assumptions!$D$33)/(Acquirer!$G$19+(Assumptions!$D$13*(1-$C30)/Assumptions!$D$6)))/Acquirer!$G$21-1 | E30: =((Acquirer!$G$15+Target!$G$15+E$27*1000*Synergies!$D$8-Synergies!$D$11-Assumptions!$D$37-(Assumptions!$D$13*$C30)*Assumptions!$D$22)*(1-Assumptions!$D$33)/(Acquirer!$G$19+(Assumptions!$D$13*(1-$C30)/Assumptions!$D$6)))/Acquirer!$G$21-1 | F30: =((Acquirer!$G$15+Target!$G$15+F$27*1000*Synergies!$D$8-Synergies!$D$11-Assumptions!$D$37-(Assumptions!$D$13*$C30)*Assumptions!$D$22)*(1-Assumptions!$D$33)/(Acquirer!$G$19+(Assumptions!$D$13*(1-$C30)/Assumptions!$D$6)))/Acquirer!$G$21-1 | G30: =((Acquirer!$G$15+Target!$G$15+G$27*1000*Synergies!$D$8-Synergies!$D$11-Assumptions!$D$37-(Assumptions!$D$13*$C30)*Assumptions!$D$22)*(1-Assumptions!$D$33)/(Acquirer!$G$19+(Assumptions!$D$13*(1-$C30)/Assumptions!$D$6)))/Acquirer!$G$21-1 | H30: =((Acquirer!$G$15+Target!$G$15+H$27*1000*Synergies!$D$8-Synergies!$D$11-Assumptions!$D$37-(Assumptions!$D$13*$C30)*Assumptions!$D$22)*(1-Assumptions!$D$33)/(Acquirer!$G$19+(Assumptions!$D$13*(1-$C30)/Assumptions!$D$6)))/Acquirer!$G$21-1
C31: 0.75 | D31: =((Acquirer!$G$15+Target!$G$15+D$27*1000*Synergies!$D$8-Synergies!$D$11-Assumptions!$D$37-(Assumptions!$D$13*$C31)*Assumptions!$D$22)*(1-Assumptions!$D$33)/(Acquirer!$G$19+(Assumptions!$D$13*(1-$C31)/Assumptions!$D$6)))/Acquirer!$G$21-1 | E31: =((Acquirer!$G$15+Target!$G$15+E$27*1000*Synergies!$D$8-Synergies!$D$11-Assumptions!$D$37-(Assumptions!$D$13*$C31)*Assumptions!$D$22)*(1-Assumptions!$D$33)/(Acquirer!$G$19+(Assumptions!$D$13*(1-$C31)/Assumptions!$D$6)))/Acquirer!$G$21-1 | F31: =((Acquirer!$G$15+Target!$G$15+F$27*1000*Synergies!$D$8-Synergies!$D$11-Assumptions!$D$37-(Assumptions!$D$13*$C31)*Assumptions!$D$22)*(1-Assumptions!$D$33)/(Acquirer!$G$19+(Assumptions!$D$13*(1-$C31)/Assumptions!$D$6)))/Acquirer!$G$21-1 | G31: =((Acquirer!$G$15+Target!$G$15+G$27*1000*Synergies!$D$8-Synergies!$D$11-Assumptions!$D$37-(Assumptions!$D$13*$C31)*Assumptions!$D$22)*(1-Assumptions!$D$33)/(Acquirer!$G$19+(Assumptions!$D$13*(1-$C31)/Assumptions!$D$6)))/Acquirer!$G$21-1 | H31: =((Acquirer!$G$15+Target!$G$15+H$27*1000*Synergies!$D$8-Synergies!$D$11-Assumptions!$D$37-(Assumptions!$D$13*$C31)*Assumptions!$D$22)*(1-Assumptions!$D$33)/(Acquirer!$G$19+(Assumptions!$D$13*(1-$C31)/Assumptions!$D$6)))/Acquirer!$G$21-1
C32: 1 | D32: =((Acquirer!$G$15+Target!$G$15+D$27*1000*Synergies!$D$8-Synergies!$D$11-Assumptions!$D$37-(Assumptions!$D$13*$C32)*Assumptions!$D$22)*(1-Assumptions!$D$33)/(Acquirer!$G$19+(Assumptions!$D$13*(1-$C32)/Assumptions!$D$6)))/Acquirer!$G$21-1 | E32: =((Acquirer!$G$15+Target!$G$15+E$27*1000*Synergies!$D$8-Synergies!$D$11-Assumptions!$D$37-(Assumptions!$D$13*$C32)*Assumptions!$D$22)*(1-Assumptions!$D$33)/(Acquirer!$G$19+(Assumptions!$D$13*(1-$C32)/Assumptions!$D$6)))/Acquirer!$G$21-1 | F32: =((Acquirer!$G$15+Target!$G$15+F$27*1000*Synergies!$D$8-Synergies!$D$11-Assumptions!$D$37-(Assumptions!$D$13*$C32)*Assumptions!$D$22)*(1-Assumptions!$D$33)/(Acquirer!$G$19+(Assumptions!$D$13*(1-$C32)/Assumptions!$D$6)))/Acquirer!$G$21-1 | G32: =((Acquirer!$G$15+Target!$G$15+G$27*1000*Synergies!$D$8-Synergies!$D$11-Assumptions!$D$37-(Assumptions!$D$13*$C32)*Assumptions!$D$22)*(1-Assumptions!$D$33)/(Acquirer!$G$19+(Assumptions!$D$13*(1-$C32)/Assumptions!$D$6)))/Acquirer!$G$21-1 | H32: =((Acquirer!$G$15+Target!$G$15+H$27*1000*Synergies!$D$8-Synergies!$D$11-Assumptions!$D$37-(Assumptions!$D$13*$C32)*Assumptions!$D$22)*(1-Assumptions!$D$33)/(Acquirer!$G$19+(Assumptions!$D$13*(1-$C32)/Assumptions!$D$6)))/Acquirer!$G$21-1
B34: Check: center cell (cash%=0%, syn=$2.0B) vs. ProForma FY2024E accretion (must = 0.000) | D34: =ROUND(F28-ProForma!D18,3)
B35: Note: incremental PP&E step-up DD&A is held fixed across both grids (a linear-approximation simplification per master spec section 4.3, since the full goodwill/PPA waterfall does not re-derive per grid cell); Grid 1's equity purchase price and new-share count are fully live and ratio-dependent.
